src/__init__.py
src/cli.py
src/controllers/__init__.py
src/controllers/init.py
src/controllers/task.py
src/editor.py
src/entrypoint.py
src/errors.py
src/models.py
src/repositories/__init__.py
src/repositories/base.py
src/repositories/errors.py
src/repositories/global_config.py
src/repositories/task.py
src/time.py
src/types.py
src/view/__init__.py
src/view/basic_list_view.py
src/view/basic_list_view_with_projects.py
src/view/basic_table_view.py
src/view/basic_table_view_with_projects.py
src/view/item_mixin.py
src/view/list.py
src/view/table.py
todo_tasks-0.1.4.dist-info/entry_points.txt
todo_tasks-0.1.4.dist-info/WHEEL
todo_tasks-0.1.4.dist-info/METADATA
todo_tasks-0.1.4.dist-info/RECORD
